epstats/__init__.py
epstats/__main__.py
epstats/config.py
epstats/locust.py
epstats/main.py
epstats/prometheus.py
epstats/py.typed
epstats/server/__init__.py
epstats/server/api.py
epstats/server/api_evaluate.py
epstats/server/api_sample_size_calculation.py
epstats/server/api_settings.py
epstats/server/json_response.py
epstats/server/req.py
epstats/server/res.py
epstats/toolkit/__init__.py
epstats/toolkit/check.py
epstats/toolkit/dao.py
epstats/toolkit/experiment.py
epstats/toolkit/metric.py
epstats/toolkit/parser.py
epstats/toolkit/results.py
epstats/toolkit/statistics.py
epstats/toolkit/utils.py
epstats/toolkit/testing/__init__.py
epstats/toolkit/testing/test_dao.py
epstats/toolkit/testing/test_data.py
epstats/toolkit/testing/utils.py
epstats/toolkit/testing/resources/.gitkeep
epstats/toolkit/testing/resources/__init__.py
epstats/toolkit/testing/resources/evaluations_checks.csv
epstats/toolkit/testing/resources/evaluations_exposures.csv
epstats/toolkit/testing/resources/evaluations_metrics.csv
epstats/toolkit/testing/resources/goals_agg.csv
epstats/toolkit/testing/resources/goals_by_unit.csv
epstats/toolkit/testing/resources/goals_simple_agg.csv
ep_stats-2.5.8.dist-info/METADATA
ep_stats-2.5.8.dist-info/WHEEL
ep_stats-2.5.8.dist-info/licenses/LICENSE
ep_stats-2.5.8.dist-info/RECORD
