Metadata-Version: 2.4
Name: ep-stats
Version: 2.5.8
Summary: Statistical package for controlled experimentation
Author-email: Ondra Zahradník <ondra.zahradnik@gmail.com>, Jan Červenka <jan.cervenka1@gendigital.com>
License-File: LICENSE
Requires-Python: >=3.11
Requires-Dist: fastapi>=0.115.11
Requires-Dist: pandas>=2.2.3
Requires-Dist: prometheus-client>=0.21.1
Requires-Dist: pydantic-settings>=2.8.1
Requires-Dist: pydantic>=2.10.6
Requires-Dist: pyparsing>=3.2.1
Requires-Dist: scipy>=1.15.2
Requires-Dist: statsmodels>=0.14.4
Requires-Dist: uvicorn>=0.34.0
